docs/ARCHITECTURE.md
docs/FFMPEG_AUDIO.md
docs/IMAGE_EXTRACTION.md
examples/README.md
examples/example_01_full_pipeline.py
examples/example_02_step_by_step.py
examples/example_03_custom_chunking.py
examples/example_04_batch_processing.py
examples/example_05_image_summarization.py
examples/example_06_advanced_usage.py
markitdown_chunker/__init__.py
markitdown_chunker/chunker.py
markitdown_chunker/cli.py
markitdown_chunker/converter.py
markitdown_chunker/exporter.py
markitdown_chunker/processor.py
markitdown_chunker-0.1.0.dist-info/licenses/LICENSE
markitdown_chunker-0.1.0.dist-info/METADATA
markitdown_chunker-0.1.0.dist-info/WHEEL
markitdown_chunker-0.1.0.dist-info/entry_points.txt
markitdown_chunker-0.1.0.dist-info/top_level.txt
markitdown_chunker-0.1.0.dist-info/RECORD
