Metadata-Version: 2.4
Name: markitdown-chunker
Version: 0.1.0
Summary: Convert documents to markdown, chunk them intelligently, and export structured data
Home-page: https://github.com/Naveenkumarar/markitdown-chunker
Author: Naveen Kumar Rajarajan
Author-email: Naveen Kumar Rajarajan <rajarajannaveenkumar@gmail.com>
License: MIT
Project-URL: Homepage, https://github.com/Naveenkumarar/markitdown-chunker
Project-URL: Bug Reports, https://github.com/Naveenkumarar/markitdown-chunker/issues
Project-URL: Source Code, https://github.com/Naveenkumarar/markitdown-chunker
Keywords: markdown,converter,chunker,document-processing,langchain,markitdown
Classifier: Development Status :: 4 - Beta
Classifier: Intended Audience :: Developers
Classifier: Topic :: Software Development :: Libraries :: Python Modules
Classifier: Topic :: Text Processing :: Markup :: Markdown
Classifier: License :: OSI Approved :: MIT License
Classifier: Programming Language :: Python :: 3
Classifier: Programming Language :: Python :: 3.8
Classifier: Programming Language :: Python :: 3.9
Classifier: Programming Language :: Python :: 3.10
Classifier: Programming Language :: Python :: 3.11
Classifier: Programming Language :: Python :: 3.12
Requires-Python: >=3.8
License-File: LICENSE
Requires-Dist: markitdown>=0.0.1
Requires-Dist: langchain>=0.1.0
Requires-Dist: langchain-text-splitters>=0.0.1
Provides-Extra: dev
Requires-Dist: pytest>=7.0.0; extra == "dev"
Requires-Dist: pytest-cov>=4.0.0; extra == "dev"
Requires-Dist: black>=23.0.0; extra == "dev"
Requires-Dist: flake8>=6.0.0; extra == "dev"
Requires-Dist: mypy>=1.0.0; extra == "dev"
Provides-Extra: images
Requires-Dist: pymupdf>=1.23.0; extra == "images"
Requires-Dist: python-docx>=0.8.11; extra == "images"
Requires-Dist: python-pptx>=0.6.21; extra == "images"
Dynamic: author
Dynamic: home-page
Dynamic: license-file
Dynamic: requires-python
